python_eol/__init__.py
python_eol/_docker_utils.py
python_eol/db.json
python_eol/db_nep.json
python_eol/main.py
python_eol-0.0.3.dist-info/LICENSE
python_eol-0.0.3.dist-info/METADATA
python_eol-0.0.3.dist-info/WHEEL
python_eol-0.0.3.dist-info/entry_points.txt
python_eol-0.0.3.dist-info/top_level.txt
python_eol-0.0.3.dist-info/RECORD
