Metadata-Version: 2.1
Name: python_eol
Version: 0.0.3
Summary: Simple tool to check if python version is past EOL
Author-email: Martin Imre <martinimre25@gmail.com>
Project-URL: Source, https://github.com/mimre25/python-eol
Classifier: License :: OSI Approved :: MIT License
Classifier: Programming Language :: Python :: 3
Classifier: Programming Language :: Python :: 3 :: Only
Requires-Python: >=3.7
License-File: LICENSE
